CODE_OF_CONDUCT.rst
LICENSE
README.rst
pyrdf2vec/__init__.py
pyrdf2vec/connectors.py
pyrdf2vec/embedders/__init__.py
pyrdf2vec/embedders/embedder.py
pyrdf2vec/embedders/fasttext.py
pyrdf2vec/embedders/word2vec.py
pyrdf2vec/graphs/__init__.py
pyrdf2vec/graphs/kg.py
pyrdf2vec/graphs/vertex.py
pyrdf2vec/rdf2vec.py
pyrdf2vec/samplers/__init__.py
pyrdf2vec/samplers/frequency.py
pyrdf2vec/samplers/pagerank.py
pyrdf2vec/samplers/sampler.py
pyrdf2vec/samplers/uniform.py
pyrdf2vec/samplers/wide.py
pyrdf2vec/typings.py
pyrdf2vec/utils/__init__.py
pyrdf2vec/utils/validation.py
pyrdf2vec/walkers/__init__.py
pyrdf2vec/walkers/anonymous.py
pyrdf2vec/walkers/community.py
pyrdf2vec/walkers/halk.py
pyrdf2vec/walkers/ngram.py
pyrdf2vec/walkers/random.py
pyrdf2vec/walkers/split.py
pyrdf2vec/walkers/walker.py
pyrdf2vec/walkers/walklet.py
pyrdf2vec/walkers/weisfeiler_lehman.py
pyrdf2vec-0.2.3.dist-info/LICENSE
pyrdf2vec-0.2.3.dist-info/WHEEL
pyrdf2vec-0.2.3.dist-info/METADATA
pyrdf2vec-0.2.3.dist-info/RECORD
