Metadata-Version: 2.1
Name: pyrdf2vec
Version: 0.2.3
Summary: Python implementation and extension of RDF2Vec
Home-page: https://github.com/IBCNServices/pyRDF2Vec
License: Ghent University and IMEC vzw
Keywords: embeddings,knowledge-graph,rdf2vec,word2vec
Author: Gilles Vandewiele
Author-email: gilles.vandewiele@ugent.be
Maintainer: Gilles Vandewiele
Maintainer-email: gilles.vandewiele@ugent.be
Requires-Python: >=3.7.1,<4.0.0
Classifier: Development Status :: 3 - Alpha
Classifier: Intended Audience :: Developers
Classifier: License :: Other/Proprietary License
Classifier: Operating System :: OS Independent
Classifier: Programming Language :: Python :: 3
Classifier: Programming Language :: Python :: 3.7
Classifier: Programming Language :: Python :: 3.8
Classifier: Programming Language :: Python :: 3.9
Classifier: Topic :: Software Development :: Build Tools
Provides-Extra: docs
Provides-Extra: lint
Provides-Extra: tests
Requires-Dist: aiohttp (>=3.7.4,<4.0.0); extra == "tests"
Requires-Dist: attrs (>=21.2.0,<22.0.0)
Requires-Dist: cachetools (>=4.2.2,<5.0.0)
Requires-Dist: gensim (>=4.0.1,<5.0.0); extra == "docs" or extra == "tests"
Requires-Dist: matplotlib (>=3.4.2,<4.0.0)
Requires-Dist: nest-asyncio (>=1.5.1,<2.0.0); extra == "tests"
Requires-Dist: networkx (>=2.5.1,<3.0.0)
Requires-Dist: numpy (>=1.20.3,<2.0.0); extra == "tests"
Requires-Dist: pandas (>=1.2.4,<2.0.0); extra == "tests"
Requires-Dist: python-Levenshtein (>=0.12.2,<0.13.0)
Requires-Dist: python-louvain (>=0.15,<0.16)
Requires-Dist: rdflib (>=5.0.0,<6.0.0); extra == "docs" or extra == "tests"
Requires-Dist: scikit-learn (>=0.24.2,<0.25.0); extra == "docs"
Requires-Dist: tomlkit (>=0.7.2,<0.8.0)
Requires-Dist: torch (>=1.8.1,<2.0.0)
Requires-Dist: tqdm (>=4.61.0,<5.0.0)
Project-URL: Bug Tracker, https://github.com/IBCNServices/pyRDF2Vec/issues
Project-URL: Documentation, https://pyrdf2vec.readthedocs.io/en/latest/
Project-URL: Repository, https://github.com/IBCNServices/pyRDF2Vec
